{
  "all": [
    "AccountAuthenticationTests",
    "AccountFileTests",
    "ChangeResolverTests",
    "DatabaseTests",
    "FileControllerUploadFileTests",
    "FileControllerUploadDeletionTests",
    "FileControllerBothUploadTests",
    "FileControllerTests",
    "UploaderTests",
    "PushNotificationTests",
    "SharingTests",
    "OtherTests",
    "UserControllerTests"
  ],
  "AccountAuthenticationTests": [
    {
      "name": "AccountAuthenticationTests.AccountAuthenticationTests_Google"
    },
    {
      "name": "AccountAuthenticationTests.AccountAuthenticationTests_Facebook"
    },
    {
      "name": "AccountAuthenticationTests.AccountAuthenticationTests_Dropbox"
    },
    {
      "name": "AccountAuthenticationTests.AccountAuthenticationTests_Microsoft"
    }
  ],
  "ChangeResolverTests": [
    {
      "name": "ChangeResolverTests.ApplyDeferredUploadsTests"
    },
    {
      "name": "ChangeResolverTests.ChangeResolverManagerTests"
    },
    {
      "name": "ChangeResolverTests.FileDeletionTests"
    }
  ],
  "DatabaseTests": [
    {
      "name": "DatabaseTests.DatabaseLockTests"
    },
    {
      "name": "DatabaseTests.DatabaseModelTests"
    },
    {
      "name": "DatabaseTests.DatabaseUpdateTests"
    },
    {
      "name": "DatabaseTests.GeneralDatabaseTests"
    },
    {
      "name": "DatabaseTests.SpecificDatabaseTests_DeferredUploadRepository"
    },
    {
      "name": "DatabaseTests.SpecificDatabaseTests_DeviceUUID"
    },
    {
      "name": "DatabaseTests.SpecificDatabaseTests_FileIndex"
    },
    {
      "name": "DatabaseTests.SpecificDatabaseTests_SharingGroups"
    },
    {
      "name": "DatabaseTests.SpecificDatabaseTests_SharingGroupUsers"
    },
    {
      "name": "DatabaseTests.SpecificDatabaseTests_SharingInvitationRepository"
    },
    {
      "name": "DatabaseTests.SpecificDatabaseTests_Uploads"
    },
    {
      "name": "DatabaseTests.SpecificDatabaseTests_UserRepository"
    }
  ],
  "FileControllerUploadFileTests": [
    {
      "name": "FileControllerUploadFileTests.FileController_FinishUploadsTests"
    },
    {
      "name": "FileControllerUploadFileTests.FileController_V0_UploadTests"
    },
    {
      "name": "FileControllerUploadFileTests.FileController_VN_UploadTests"
    }
  ],
  "FileControllerUploadDeletionTests": [
    {
      "name": "FileControllerUploadDeletionTests.FileController_FinishUploadsTests"
    },
    {
      "name": "FileControllerUploadDeletionTests.FileController_UploadDeletionTests"
    }
  ],
  "FileControllerBothUploadTests": [
    {
      "name": "FileControllerBothUploadTests.FileController_BothUploadSeparateTests"
    },
    {
      "name": "FileControllerBothUploadTests.FileController_UploadsOverlapTests"
    }
  ],
  "UploaderTests": [
    {
      "name": "UploaderTests.PruneTests"
    },
    {
      "name": "UploaderTests.UploaderFileChangeTests"
    },
    {
      "name": "UploaderTests.UploaderFileDeletionTests"
    }
  ],
  "FileControllerTests": [
    {
      "name": "FileControllerTests.FileController_DownloadAppMetaDataTests",
      "parameters": [
        "MOCK_STORAGE" 
       ]
    },
    {
      "name": "FileControllerTests.FileController_DownloadTests"
    },
    {
      "name": "FileControllerTests.FileController_GetUploadsResults"
    },
    {
      "name": "FileControllerTests.FileController_IndexTests",
      "parameters": [
        "MOCK_STORAGE" 
       ]
    }
  ],
  "PushNotificationTests": [
    {
      "name": "PushNotificationTests.SendPushNotificationsTests"
    },
    {
      "name": "PushNotificationTests.RegisterPushNotificationsTest"
    }
  ],
  "AccountFileTests": [
    {
      "name": "AccountFileTests.MockStorageTests",
      "parameters": [
        "MOCK_STORAGE" 
       ]
    },
    {
      "name": "AccountFileTests.MockStorageLiveTests",
      "parameters": [
        "MOCK_STORAGE"
      ]
    }
  ],
  "SharingTests": [
    {
      "name": "SharingTests.Sharing_FileManipulationTests"
    },
    {
      "name": "SharingTests.SharingAccountsController_CreateSharingInvitation"
    },
    {
      "name": "SharingTests.SharingAccountsController_GetSharingInvitationInfo"
    },
    {
      "name": "SharingTests.SharingAccountsController_RedeemSharingInvitation"
    },
    {
      "name": "SharingTests.SharingGroupsControllerTests"
    }
  ],
  "OtherTests": [
    {
      "name": "OtherTests.FailureTests"
    },
    {
      "name": "OtherTests.HealthCheckTests"
    },
    {
      "name": "OtherTests.MessageTests"
    },
    {
      "name": "OtherTests.VersionTests"
    },
    {
      "name": "OtherTests.RepeatingTimerTests"
    }
  ],
  "UserControllerTests": [
    {
      "name": "UserControllerTests.UserControllerTests"
    }
  ]
}
